bdf2ttf/__init__.py
bdf2ttf/convert.py
bdf2ttf/feature.py
bdf2ttf-0.0.5.dist-info/LICENSE
bdf2ttf-0.0.5.dist-info/METADATA
bdf2ttf-0.0.5.dist-info/WHEEL
bdf2ttf-0.0.5.dist-info/entry_points.txt
bdf2ttf-0.0.5.dist-info/top_level.txt
bdf2ttf-0.0.5.dist-info/RECORD
