Metadata-Version: 2.1
Name: bdf2ttf
Version: 0.0.5
Summary: Convert bitmap fonts into TTF format
Home-page: UNKNOWN
Author: Gabriel Holodak
License: UNKNOWN
Platform: UNKNOWN
Classifier: License :: OSI Approved :: GNU General Public License v3 (GPLv3)
Requires-Python: >=3
License-File: LICENSE
Requires-Dist: bdflib
Requires-Dist: pyyaml
